{
  "_class": "text",
  "attributedString": {
    "_class": "attributedString",
    "attributes": [
      {
        "_class": "stringAttribute",
        "attributes": {
          "MSAttributedStringColorAttribute": {
            "_class": "color",
            "alpha": 1,
            "blue": 0.1764705882352941,
            "green": 0.1764705882352941,
            "red": 0.1764705882352941
          },
          "MSAttributedStringFontAttribute": {
            "_class": "fontDescriptor",
            "attributes": {
              "name": "Overpass-Regular",
              "size": 13
            }
          },
          "kerning": 0,
          "paragraphStyle": {
            "_class": "paragraphStyle",
            "alignment": 2,
            "allowsDefaultTighteningForTruncation": 0
          },
          "strikethroughStyle": 0,
          "textStyleVerticalAlignmentKey": 0,
          "underlineStyle": 1
        },
        "length": 14,
        "location": 0
      }
    ],
    "string": "See all brands"
  },
  "automaticallyDrawOnUnderlyingPath": false,
  "booleanOperation": -1,
  "clippingMaskMode": 0,
  "do_objectID": "F8EB5FFD-F560-4E03-BF45-B9266C2877E7",
  "dontSynchroniseWithSymbol": false,
  "exportOptions": {
    "_class": "exportOptions",
    "do_objectID": "23913021-E063-421A-982A-97D903ADD02E",
    "exportFormats": [
    ],
    "includedLayerIds": [
    ],
    "layerOptions": 0,
    "shouldTrim": false
  },
  "frame": {
    "_class": "rect",
    "constrainProportions": false,
    "do_objectID": "C2AD0EDA-0EE5-4359-A16E-4F349B270C02",
    "height": 17,
    "width": 82,
    "x": 80,
    "y": 57
  },
  "glyphBounds": "{{0, 3}, {81, 11}}",
  "hasClippingMask": false,
  "isFixedToViewport": false,
  "isFlippedHorizontal": false,
  "isFlippedVertical": false,
  "isLocked": false,
  "isVisible": true,
  "layerListExpandedType": 0,
  "lineSpacingBehaviour": 2,
  "name": "See all brands",
  "nameIsFixed": false,
  "resizingConstraint": 47,
  "resizingType": 0,
  "rotation": 0,
  "sharedStyleID": "58C9118F-6BB2-4FE4-8DF4-EC10E11E43C8",
  "shouldBreakMaskChain": false,
  "style": {
    "_class": "style",
    "do_objectID": "8465D131-B4A8-417F-B7E8-26A9D3155CBF",
    "endMarkerType": 0,
    "miterLimit": 10,
    "startMarkerType": 0,
    "textStyle": {
      "_class": "textStyle",
      "do_objectID": "FD0E5F95-EF8B-4D79-9171-91069742A4AC",
      "encodedAttributes": {
        "MSAttributedStringColorAttribute": {
          "_class": "color",
          "alpha": 1,
          "blue": 0.1764705882352941,
          "green": 0.1764705882352941,
          "red": 0.1764705882352941
        },
        "MSAttributedStringFontAttribute": {
          "_class": "fontDescriptor",
          "attributes": {
            "name": "Overpass-Regular",
            "size": 13
          }
        },
        "kerning": 0,
        "paragraphStyle": {
          "_class": "paragraphStyle",
          "alignment": 2,
          "allowsDefaultTighteningForTruncation": 0
        },
        "strikethroughStyle": 0,
        "textStyleVerticalAlignmentKey": 0,
        "underlineStyle": 1
      },
      "verticalAlignment": 1
    },
    "windingRule": 1
  },
  "textBehaviour": 0
}