{
  "_class": "group",
  "booleanOperation": -1,
  "clippingMaskMode": 0,
  "do_objectID": "E5B2C31D-B134-49BC-9134-799B42B4EFE7",
  "exportOptions": {
    "_class": "exportOptions",
    "do_objectID": "FA973552-5009-4DF4-A041-821821B3F282",
    "exportFormats": [
    ],
    "includedLayerIds": [
    ],
    "layerOptions": 0,
    "shouldTrim": false
  },
  "frame": {
    "_class": "rect",
    "constrainProportions": false,
    "do_objectID": "1FCDE8C4-31C0-415E-AC2D-828157C4A059",
    "height": 143,
    "width": 400,
    "x": 0,
    "y": 0
  },
  "groupLayout": {
    "_class": "MSImmutableFreeformGroupLayout",
    "do_objectID": "FC44B6E3-918D-4626-8664-EF572413B0F3"
  },
  "hasClickThrough": false,
  "hasClippingMask": false,
  "isFixedToViewport": false,
  "isFlippedHorizontal": false,
  "isFlippedVertical": false,
  "isLocked": false,
  "isVisible": true,
  "layerListExpandedType": 0,
  "layers": [
    {
      "class": "rectangle",
      "id": "E638257A-492B-476C-959C-267B9298941B"
    },
    {
      "class": "text",
      "id": "50A3344F-4CDF-44D3-8AA7-FB97D98B9819"
    }
  ],
  "name": "Typo",
  "nameIsFixed": true,
  "resizingConstraint": 63,
  "resizingType": 0,
  "rotation": 0,
  "shouldBreakMaskChain": false,
  "style": {
    "_class": "style",
    "do_objectID": "4E65F1C1-AFA1-48CC-8FB5-94DF975EC9B0",
    "endMarkerType": 0,
    "miterLimit": 10,
    "startMarkerType": 0,
    "windingRule": 1
  }
}