{
  "_class": "group",
  "booleanOperation": -1,
  "clippingMaskMode": 0,
  "do_objectID": "807A5EAB-003A-49D0-92A2-BD89553D7489",
  "exportOptions": {
    "_class": "exportOptions",
    "do_objectID": "39317F72-829D-4FE6-BF21-F6E4D345C33A",
    "exportFormats": [
    ],
    "includedLayerIds": [
    ],
    "layerOptions": 0,
    "shouldTrim": false
  },
  "frame": {
    "_class": "rect",
    "constrainProportions": false,
    "do_objectID": "5E112BFB-3F80-4C3C-944B-B0AD6A2C0FC7",
    "height": 24,
    "width": 60,
    "x": 30.97637795275588,
    "y": 25
  },
  "groupLayout": {
    "_class": "MSImmutableFreeformGroupLayout",
    "do_objectID": "810ABAF8-2A64-48F1-BCE6-8A6B95AB0C38"
  },
  "hasClickThrough": false,
  "hasClippingMask": false,
  "isFixedToViewport": false,
  "isFlippedHorizontal": false,
  "isFlippedVertical": false,
  "isLocked": false,
  "isVisible": true,
  "layerListExpandedType": 2,
  "layers": [
    {
      "class": "bitmap",
      "id": "1A49BAF3-5333-4E0E-A1AB-96A5EF68300F"
    }
  ],
  "name": "Logo",
  "nameIsFixed": true,
  "resizingConstraint": 61,
  "resizingType": 0,
  "rotation": 0,
  "shouldBreakMaskChain": false,
  "style": {
    "_class": "style",
    "do_objectID": "31A62522-95B0-4D20-991E-7D930938247A",
    "endMarkerType": 0,
    "miterLimit": 10,
    "startMarkerType": 0,
    "windingRule": 1
  }
}