{
  "_class": "group",
  "booleanOperation": -1,
  "clippingMaskMode": 0,
  "do_objectID": "F74FFD5C-0444-4D70-A71C-91D9C18E2D6C",
  "exportOptions": {
    "_class": "exportOptions",
    "do_objectID": "DC794212-CC19-4C32-AEEC-333E61D197DF",
    "exportFormats": [
    ],
    "includedLayerIds": [
    ],
    "layerOptions": 0,
    "shouldTrim": false
  },
  "frame": {
    "_class": "rect",
    "constrainProportions": false,
    "do_objectID": "291397C4-A325-41B9-8B3E-C230BA0FC2F2",
    "height": 60,
    "width": 60,
    "x": 400,
    "y": 0
  },
  "groupLayout": {
    "_class": "MSImmutableFreeformGroupLayout",
    "do_objectID": "7544B007-58EC-4115-89BE-336B35952A40"
  },
  "hasClickThrough": false,
  "hasClippingMask": false,
  "isFixedToViewport": false,
  "isFlippedHorizontal": false,
  "isFlippedVertical": false,
  "isLocked": false,
  "isVisible": true,
  "layerListExpandedType": 1,
  "layers": [
    {
      "class": "rectangle",
      "id": "80B3001F-4371-4B6A-A001-252B6C4E9AE2"
    }
  ],
  "name": "Icon Copy 5",
  "nameIsFixed": true,
  "resizingConstraint": 63,
  "resizingType": 0,
  "rotation": 0,
  "shouldBreakMaskChain": false,
  "style": {
    "_class": "style",
    "do_objectID": "A1C7988A-3D55-4411-BD6D-7484D01DC1F0",
    "endMarkerType": 0,
    "miterLimit": 10,
    "startMarkerType": 0,
    "windingRule": 1
  }
}