{
  "_class": "symbolInstance",
  "booleanOperation": -1,
  "clippingMaskMode": 0,
  "do_objectID": "BC659A15-A874-42D9-ABE8-77CD71387FEF",
  "exportOptions": {
    "_class": "exportOptions",
    "do_objectID": "B8EA2FDC-DD93-4440-A7D0-F35ACED8319E",
    "exportFormats": [
    ],
    "includedLayerIds": [
    ],
    "layerOptions": 0,
    "shouldTrim": false
  },
  "frame": {
    "_class": "rect",
    "constrainProportions": false,
    "do_objectID": "EB700EFD-0920-4019-B737-C8DDE0C91D46",
    "height": 35,
    "width": 35,
    "x": 270,
    "y": 0
  },
  "hasClippingMask": false,
  "horizontalSpacing": 0,
  "isFixedToViewport": false,
  "isFlippedHorizontal": false,
  "isFlippedVertical": false,
  "isLocked": false,
  "isVisible": true,
  "layerListExpandedType": 0,
  "name": "Check (Size)",
  "nameIsFixed": false,
  "overrideValues": [
  ],
  "resizingConstraint": 63,
  "resizingType": 0,
  "rotation": 0,
  "scale": 1,
  "shouldBreakMaskChain": false,
  "style": {
    "_class": "style",
    "do_objectID": "D6CC82DC-67D0-45FB-9661-A9ACF75E42C0",
    "endMarkerType": 0,
    "miterLimit": 10,
    "startMarkerType": 0,
    "windingRule": 1
  },
  "symbolID": "584CD0C1-463D-436B-A33A-12DF483F40B6",
  "verticalSpacing": 0
}